__init__.py
fastapi_exception_responses/__init__.py
fastapi_exception_responses/core.py
fastapi_exception_responses-0.3.1.dist-info/licenses/LICENSE
fastapi_exception_responses-0.3.1.dist-info/METADATA
fastapi_exception_responses-0.3.1.dist-info/WHEEL
fastapi_exception_responses-0.3.1.dist-info/top_level.txt
fastapi_exception_responses-0.3.1.dist-info/RECORD
