Metadata-Version: 2.4
Name: fastapi-exception-responses
Version: 0.3.1
Summary: fastapi-responses generates HTTPExceptions and OpenAPI description for status codes
Author-email: max31ru12 <maxevg72@gmail.com>
License: MIT
Project-URL: Repository, https://github.com/max31ru12/fastapi-responses
Requires-Python: >=3.9
License-File: LICENSE
Requires-Dist: starlette<0.47.0,>=0.46.2
Dynamic: license-file
